{
	"info": {
		"_postman_id": "12353e3c-d259-4d58-a6e7-88cde3c79ae0",
		"name": "YSW",
		"schema": "https://schema.getpostman.com/json/collection/v2.1.0/collection.json",
		"_exporter_id": "15734739"
	},
	"item": [
		{
			"name": "structure",
			"item": [
				{
					"name": "getAllStructures",
					"request": {
						"method": "GET",
						"header": [],
						"url": {
							"raw": "http://localhost:3000/structure/getAllStructures",
							"protocol": "http",
							"host": [
								"localhost"
							],
							"port": "3000",
							"path": [
								"structure",
								"getAllStructures"
							]
						}
					},
					"response": []
				},
				{
					"name": "getStructureById",
					"request": {
						"method": "GET",
						"header": [],
						"url": {
							"raw": "http://localhost:3000/structure/getStructuresByName/teste",
							"protocol": "http",
							"host": [
								"localhost"
							],
							"port": "3000",
							"path": [
								"structure",
								"getStructuresByName",
								"teste"
							]
						}
					},
					"response": []
				},
				{
					"name": "createStructure",
					"request": {
						"method": "POST",
						"header": [],
						"body": {
							"mode": "raw",
							"raw": "{\r\n    \"name\": \"teste2\",\r\n    \"description\": \"teste2\"\r\n}",
							"options": {
								"raw": {
									"language": "json"
								}
							}
						},
						"url": {
							"raw": "http://localhost:3000/structure/createStructure",
							"protocol": "http",
							"host": [
								"localhost"
							],
							"port": "3000",
							"path": [
								"structure",
								"createStructure"
							]
						}
					},
					"response": []
				},
				{
					"name": "createStructure Copy",
					"request": {
						"method": "DELETE",
						"header": [],
						"body": {
							"mode": "raw",
							"raw": "{\r\n    \"name\": \"teste2\"\r\n}",
							"options": {
								"raw": {
									"language": "json"
								}
							}
						},
						"url": {
							"raw": "http://localhost:3000/structure/deleteStructure",
							"protocol": "http",
							"host": [
								"localhost"
							],
							"port": "3000",
							"path": [
								"structure",
								"deleteStructure"
							]
						}
					},
					"response": []
				}
			]
		},
		{
			"name": "tag",
			"item": [
				{
					"name": "getAllTags",
					"request": {
						"method": "GET",
						"header": [],
						"url": {
							"raw": "http://localhost:3000/tag/getAll",
							"protocol": "http",
							"host": [
								"localhost"
							],
							"port": "3000",
							"path": [
								"tag",
								"getAll"
							]
						}
					},
					"response": []
				},
				{
					"name": "getStructureById",
					"request": {
						"method": "GET",
						"header": [],
						"url": {
							"raw": "http://localhost:3000/structure/getStructuresByName/teste",
							"protocol": "http",
							"host": [
								"localhost"
							],
							"port": "3000",
							"path": [
								"structure",
								"getStructuresByName",
								"teste"
							]
						}
					},
					"response": []
				},
				{
					"name": "createTag",
					"request": {
						"method": "POST",
						"header": [],
						"body": {
							"mode": "raw",
							"raw": "{\r\n    \"name\": \"teste3\",\r\n    \"id_structure\": \"e5fc7b1d-9646-48d9-b311-9ea74e7ce843\"\r\n}",
							"options": {
								"raw": {
									"language": "json"
								}
							}
						},
						"url": {
							"raw": "http://localhost:3000/tag/create",
							"protocol": "http",
							"host": [
								"localhost"
							],
							"port": "3000",
							"path": [
								"tag",
								"create"
							]
						}
					},
					"response": []
				},
				{
					"name": "createStructure Copy",
					"request": {
						"method": "DELETE",
						"header": [],
						"body": {
							"mode": "raw",
							"raw": "{\r\n    \"name\": \"4754a163-df58-44d8-ac5c-c7cac75c1949\"\r\n}",
							"options": {
								"raw": {
									"language": "json"
								}
							}
						},
						"url": {
							"raw": "http://localhost:3000/tag/delete",
							"protocol": "http",
							"host": [
								"localhost"
							],
							"port": "3000",
							"path": [
								"tag",
								"delete"
							]
						}
					},
					"response": []
				}
			]
		},
		{
			"name": "user",
			"item": [
				{
					"name": "getAllUsers",
					"request": {
						"method": "GET",
						"header": [],
						"url": {
							"raw": "http://localhost:3000/user/getAll",
							"protocol": "http",
							"host": [
								"localhost"
							],
							"port": "3000",
							"path": [
								"user",
								"getAll"
							]
						}
					},
					"response": []
				},
				{
					"name": "getStructureById",
					"request": {
						"method": "GET",
						"header": [],
						"url": {
							"raw": "http://localhost:3000/structure/getStructuresByName/teste",
							"protocol": "http",
							"host": [
								"localhost"
							],
							"port": "3000",
							"path": [
								"structure",
								"getStructuresByName",
								"teste"
							]
						}
					},
					"response": []
				},
				{
					"name": "createUser",
					"request": {
						"method": "POST",
						"header": [],
						"body": {
							"mode": "raw",
							"raw": "{\r\n    \"name\": \"teste3\",\r\n    \"email\": \"e5fc7b1d-9646-48d9-b311-9ea74e7ce843\",\r\n    \"pass\": \"123\",\r\n    \"manager\": \"escola\"\r\n}",
							"options": {
								"raw": {
									"language": "json"
								}
							}
						},
						"url": {
							"raw": "http://localhost:3000/user/create",
							"protocol": "http",
							"host": [
								"localhost"
							],
							"port": "3000",
							"path": [
								"user",
								"create"
							]
						}
					},
					"response": []
				},
				{
					"name": "createStructure Copy",
					"request": {
						"method": "DELETE",
						"header": [],
						"body": {
							"mode": "raw",
							"raw": "{\r\n    \"name\": \"4754a163-df58-44d8-ac5c-c7cac75c1949\"\r\n}",
							"options": {
								"raw": {
									"language": "json"
								}
							}
						},
						"url": {
							"raw": "http://localhost:3000/tag/delete",
							"protocol": "http",
							"host": [
								"localhost"
							],
							"port": "3000",
							"path": [
								"tag",
								"delete"
							]
						}
					},
					"response": []
				}
			]
		}
	]
}